baize-0.23.1.dist-info/METADATA
baize-0.23.1.dist-info/WHEEL
baize-0.23.1.dist-info/entry_points.txt
baize-0.23.1.dist-info/licenses/LICENSE
baize/__init__.py
baize/__version__.py
baize/asgi/__init__.py
baize/asgi/helper.py
baize/asgi/middleware.py
baize/asgi/requests.py
baize/asgi/responses.py
baize/asgi/routing.py
baize/asgi/shortcut.py
baize/asgi/staticfiles.py
baize/asgi/websocket.py
baize/concurrency.py
baize/datastructures.py
baize/exceptions.py
baize/multipart.py
baize/multipart_helper.py
baize/py.typed
baize/requests.py
baize/responses.py
baize/routing.py
baize/staticfiles.py
baize/typing.py
baize/utils.py
baize/wsgi/__init__.py
baize/wsgi/middleware.py
baize/wsgi/requests.py
baize/wsgi/responses.py
baize/wsgi/routing.py
baize/wsgi/shortcut.py
baize/wsgi/staticfiles.py
baize-0.23.1.dist-info/RECORD
