Metadata-Version: 2.1
Name: baize
Version: 0.23.1
Summary: Powerful and exquisite WSGI/ASGI framework/toolkit.
Author-Email: abersheeran <me@abersheeran.com>
License: Apache-2.0
Classifier: Programming Language :: Python :: 3
Classifier: Programming Language :: Python :: Implementation :: CPython
Classifier: Programming Language :: Python :: Implementation :: PyPy
Classifier: Topic :: Internet :: WWW/HTTP
Classifier: Topic :: Internet :: WWW/HTTP :: WSGI
Classifier: Topic :: Internet :: WWW/HTTP :: WSGI :: Application
Project-URL: Homepage, https://github.com/abersheeran/baize
Project-URL: Repository, https://github.com/abersheeran/baize
Project-URL: Documentation, https://baize.aber.sh/
Requires-Python: >=3.9
